autobigs/cli/__init__.py
autobigs/cli/info.py
autobigs/cli/meta.py
autobigs/cli/program.py
autobigs/cli/st.py
autobigs_cli-0.6.5.dist-info/LICENSE
autobigs_cli-0.6.5.dist-info/METADATA
autobigs_cli-0.6.5.dist-info/WHEEL
autobigs_cli-0.6.5.dist-info/entry_points.txt
autobigs_cli-0.6.5.dist-info/top_level.txt
autobigs_cli-0.6.5.dist-info/RECORD
