Metadata-Version: 2.2
Name: autoBIGS.cli
Version: 0.6.5
Summary: A CLI tool to rapidly fetch fetch MLST profiles given sequences for various diseases.
License: GPL-3.0-or-later
Project-URL: Repository, https://github.com/Syph-and-VPD-Lab/autoBIGS.cli
Project-URL: Issues, https://github.com/Syph-and-VPD-Lab/autoBIGS.cli/issues
Requires-Python: >=3.12
License-File: LICENSE
Requires-Dist: autoBIGS-engine==0.14.*
